wordcraft/__init__.py
wordcraft/wordcraft.py
wordcraft-0.1.dist-info/METADATA
wordcraft-0.1.dist-info/WHEEL
wordcraft-0.1.dist-info/top_level.txt
wordcraft-0.1.dist-info/RECORD
