Metadata-Version: 2.1
Name: wordcraft
Version: 0.1
Summary: A Library for Training Language Models with LSTM in TensorFlow
Home-page: https://github.com/IMApurbo/wordcraft
Author: AKM Korishee Apurbo
Author-email: bandinvisible8@gmail.com
Classifier: Programming Language :: Python :: 3
Classifier: License :: OSI Approved :: MIT License
Classifier: Operating System :: OS Independent
Requires-Python: >=3.6
Requires-Dist: tensorflow>=2.0.0
Requires-Dist: numpy>=1.19.0
Requires-Dist: pickle-mixin>=1.0.0
